address_picker/__init__.py
address_picker/admin.py
address_picker/apps.py
address_picker/forms.py
address_picker/models.py
address_picker/tests.py
address_picker/urls.py
address_picker/views.py
address_picker/management/commands/__init__.py
address_picker/management/commands/load_nepali_addresses.py
address_picker/migrations/0001_initial.py
address_picker/migrations/__init__.py
address_picker/templates/base.html
address_picker/templates/address_picker/address_picker.html
django_nepali_address_picker-0.1.2.dist-info/licenses/LICENSE
nepali_address_picker/__init__.py
nepali_address_picker/asgi.py
nepali_address_picker/settings.py
nepali_address_picker/urls.py
nepali_address_picker/wsgi.py
django_nepali_address_picker-0.1.2.dist-info/METADATA
django_nepali_address_picker-0.1.2.dist-info/WHEEL
django_nepali_address_picker-0.1.2.dist-info/top_level.txt
django_nepali_address_picker-0.1.2.dist-info/RECORD
